meuinss/__init__.py
meuinss/bpc.py
meuinss-0.1.13.dist-info/METADATA
meuinss-0.1.13.dist-info/WHEEL
meuinss-0.1.13.dist-info/RECORD
