Metadata-Version: 2.1
Name: meuinss
Version: 0.1.13
Summary: 
Author: Rogelho Junior
Author-email: rogelho.fernandes@grupobyx.com.br
Requires-Python: >=3.10,<3.13
Classifier: Programming Language :: Python :: 3
Classifier: Programming Language :: Python :: 3.10
Classifier: Programming Language :: Python :: 3.11
Classifier: Programming Language :: Python :: 3.12
Requires-Dist: requests (>=2.32.3,<3.0.0)
Requires-Dist: requests-ip-rotator (>=1.0.14,<2.0.0)
